README.rst
setup.py
ircclient/__init__.py
ircclient/client.py
ircclient/const.py
ircclient/socket.py
ircclient/struct.py
ircclient/version.txt
ircclient.egg-info/PKG-INFO
ircclient.egg-info/SOURCES.txt
ircclient.egg-info/dependency_links.txt
ircclient.egg-info/requires.txt
ircclient.egg-info/top_level.txt