Metadata-Version: 1.0
Name: ircclient
Version: 0.2.1
Summary: Simple client interface.
Home-page: https://github.com/youknowone/ircclient
Author: Jeong YunWon
Author-email: jeong+ircclient@youknowone.org
License: UNKNOWN
Platform: UNKNOWN
